bloom_filter_mod.py
drs_bloom_filter-2.4.dist-info/METADATA
drs_bloom_filter-2.4.dist-info/WHEEL
drs_bloom_filter-2.4.dist-info/top_level.txt
drs_bloom_filter-2.4.dist-info/RECORD
