Metadata-Version: 2.1
Name: drs-bloom-filter
Version: 2.4
Summary: Pure Python Bloom Filter module
Home-page: http://stromberg.dnsalias.org/~strombrg/drs-bloom-filter/
Author: Daniel Richard Stromberg
Author-email: strombrg@gmail.com
License: MIT
Keywords: probabilistic set datastructure
Platform: Cross platform
Classifier: Development Status :: 5 - Production/Stable
Classifier: Intended Audience :: Developers
Classifier: Programming Language :: Python :: 3
